AUTHORS
ChangeLog
LICENSE
MANIFEST.in
README.rst
babel-django.cfg
babel-djangojs.cfg
manage.py
requirements.txt
run_tests.sh
setup.cfg
setup.py
test-requirements.txt
tox.ini
devstack/plugin.sh
devstack/settings
doc/Makefile
doc/source/conf.py
doc/source/index.rst
doc/source/releases/0.1.0.rst
magnum_ui/__init__.py
magnum_ui/models.py
magnum_ui/version.py
magnum_ui/api/__init__.py
magnum_ui/api/magnum.py
magnum_ui/api/rest/__init__.py
magnum_ui/api/rest/magnum.py
magnum_ui/content/__init__.py
magnum_ui/content/baymodels/__init__.py
magnum_ui/content/baymodels/panel.py
magnum_ui/content/baymodels/tests.py
magnum_ui/content/baymodels/urls.py
magnum_ui/content/baymodels/views.py
magnum_ui/content/bays/__init__.py
magnum_ui/content/bays/panel.py
magnum_ui/content/bays/tests.py
magnum_ui/content/bays/urls.py
magnum_ui/content/bays/views.py
magnum_ui/enabled/_1370_project_container-infra_panelgroup.py
magnum_ui/enabled/_1371_project_container-infra_bays_panel.py
magnum_ui/enabled/_1372_project_container-infra_baymodels_panel.py
magnum_ui/locale/cs/LC_MESSAGES/django.po
magnum_ui/locale/cs/LC_MESSAGES/djangojs.po
magnum_ui/locale/de/LC_MESSAGES/django.po
magnum_ui/locale/en_GB/LC_MESSAGES/django.po
magnum_ui/locale/en_GB/LC_MESSAGES/djangojs.po
magnum_ui/locale/fr/LC_MESSAGES/django.po
magnum_ui/locale/ja/LC_MESSAGES/django.po
magnum_ui/locale/ja/LC_MESSAGES/djangojs.po
magnum_ui/locale/ko_KR/LC_MESSAGES/django.po
magnum_ui/locale/ko_KR/LC_MESSAGES/djangojs.po
magnum_ui/locale/pt_BR/LC_MESSAGES/django.po
magnum_ui/locale/pt_BR/LC_MESSAGES/djangojs.po
magnum_ui/locale/ru/LC_MESSAGES/django.po
magnum_ui/locale/ru/LC_MESSAGES/djangojs.po
magnum_ui/locale/zh_CN/LC_MESSAGES/django.po
magnum_ui/locale/zh_CN/LC_MESSAGES/djangojs.po
magnum_ui/locale/zh_TW/LC_MESSAGES/django.po
magnum_ui/static/dashboard/container-infra/container-infra.module.js
magnum_ui/static/dashboard/container-infra/container-infra.module.spec.js
magnum_ui/static/dashboard/container-infra/container-infra.scss
magnum_ui_horizon.egg-info/PKG-INFO
magnum_ui_horizon.egg-info/SOURCES.txt
magnum_ui_horizon.egg-info/dependency_links.txt
magnum_ui_horizon.egg-info/not-zip-safe
magnum_ui_horizon.egg-info/pbr.json
magnum_ui_horizon.egg-info/requires.txt
magnum_ui_horizon.egg-info/top_level.txt
